[
	{
		"id": 18,
		"name": "Twitch",
		"img": "http://ddragon.leagueoflegends.com/cdn/4.9.1/img/champion/Twitch.png",
		"games": 88
	},
	{
		"id": 19,
		"name": "Braum",
		"img": "http://ddragon.leagueoflegends.com/cdn/4.9.1/img/champion/Braum.png",
		"games": 140
	},
	{
		"id": 20,
		"name": "Syndra",
		"img": "http://ddragon.leagueoflegends.com/cdn/4.9.1/img/champion/Syndra.png",
		"games": 14
	},
	{
		"id": 21,
		"name": "Caitlyn",
		"img": "http://ddragon.leagueoflegends.com/cdn/4.9.1/img/champion/Caitlyn.png",
		"games": 27
	},
	{
		"id": 14,
		"name": "Thresh",
		"img": "http://ddragon.leagueoflegends.com/cdn/4.9.1/img/champion/Thresh.png",
		"games": 98
	},
	{
		"id": 10,
		"name": "Ahri",
		"img": "http://ddragon.leagueoflegends.com/cdn/4.9.1/img/champion/Ahri.png",
		"games": 114
	}
]

